fhircraft/__init__.py
fhircraft/config.py
fhircraft/utils.py
fhircraft/fhir/__init__.py
fhircraft/fhir/mapper/__init__.py
fhircraft/fhir/mapper/lexer.py
fhircraft/fhir/mapper/parser.py
fhircraft/fhir/mapper/engine/__init__.py
fhircraft/fhir/mapper/engine/core.py
fhircraft/fhir/mapper/engine/exceptions.py
fhircraft/fhir/mapper/engine/scope.py
fhircraft/fhir/mapper/engine/transformer.py
fhircraft/fhir/packages/__init__.py
fhircraft/fhir/packages/client.py
fhircraft/fhir/packages/models.py
fhircraft/fhir/path/__init__.py
fhircraft/fhir/path/exceptions.py
fhircraft/fhir/path/lexer.py
fhircraft/fhir/path/mixin.py
fhircraft/fhir/path/parser.py
fhircraft/fhir/path/utils.py
fhircraft/fhir/path/engine/__init__.py
fhircraft/fhir/path/engine/additional.py
fhircraft/fhir/path/engine/aggregates.py
fhircraft/fhir/path/engine/boolean.py
fhircraft/fhir/path/engine/collection.py
fhircraft/fhir/path/engine/combining.py
fhircraft/fhir/path/engine/comparison.py
fhircraft/fhir/path/engine/conversion.py
fhircraft/fhir/path/engine/core.py
fhircraft/fhir/path/engine/environment.py
fhircraft/fhir/path/engine/equality.py
fhircraft/fhir/path/engine/existence.py
fhircraft/fhir/path/engine/filtering.py
fhircraft/fhir/path/engine/literals.py
fhircraft/fhir/path/engine/math.py
fhircraft/fhir/path/engine/navigation.py
fhircraft/fhir/path/engine/strings.py
fhircraft/fhir/path/engine/subsetting.py
fhircraft/fhir/path/engine/types.py
fhircraft/fhir/path/engine/ucum_to_pint.txt
fhircraft/fhir/path/engine/utility.py
fhircraft/fhir/resources/__init__.py
fhircraft/fhir/resources/base.py
fhircraft/fhir/resources/factory.py
fhircraft/fhir/resources/generator.py
fhircraft/fhir/resources/repository.py
fhircraft/fhir/resources/resource_template.py.j2
fhircraft/fhir/resources/validators.py
fhircraft/fhir/resources/datatypes/__init__.py
fhircraft/fhir/resources/datatypes/primitives.py
fhircraft/fhir/resources/datatypes/utils.py
fhircraft/fhir/resources/datatypes/R4/__init__.py
fhircraft-0.6.0.dist-info/METADATA
fhircraft-0.6.0.dist-info/WHEEL
fhircraft-0.6.0.dist-info/licenses/LICENSE
fhircraft-0.6.0.dist-info/RECORD
