Metadata-Version: 2.4
Name: fhircraft
Version: 0.6.0
Summary: Fhircraft transforms FHIR (Fast Healthcare Interoperability Resources) specifications into type-safe Python models using Pydantic. Build healthcare applications with automatic validation, intelligent code completion, and seamless integration with Python's ecosystem.
Project-URL: Homepage, https://github.com/luisfabib/fhircraft
Project-URL: Issues, https://github.com/luisfabib/fhircraft/issues
Project-URL: Documentation, https://luisfabib.github.io/fhircraft/
Author-email: Luis Fábregas-Ibáñez <luisfabib@gmail.com>
License: The MIT License (MIT)
License-File: LICENSE
Keywords: FHIR,Pydantic,healthcare,modelling,validation
Classifier: Development Status :: 3 - Alpha
Classifier: Environment :: Console
Classifier: Environment :: MacOS X
Classifier: Framework :: Pydantic
Classifier: Intended Audience :: Developers
Classifier: Intended Audience :: Healthcare Industry
Classifier: Intended Audience :: Information Technology
Classifier: Intended Audience :: System Administrators
Classifier: License :: OSI Approved :: MIT License
Classifier: Operating System :: POSIX :: Linux
Classifier: Operating System :: Unix
Classifier: Programming Language :: Python
Classifier: Programming Language :: Python :: 3
Classifier: Programming Language :: Python :: 3 :: Only
Classifier: Programming Language :: Python :: 3.10
Classifier: Programming Language :: Python :: 3.11
Classifier: Programming Language :: Python :: 3.12
Classifier: Programming Language :: Python :: 3.13
Classifier: Topic :: Software Development :: Libraries :: Python Modules
Requires-Python: >=3.10
Requires-Dist: jinja2>=3.1
Requires-Dist: jsonpath-ng>1
Requires-Dist: jsonschema>4
Requires-Dist: packaging>=25
Requires-Dist: pint>=0.24
Requires-Dist: ply>=3.11
Requires-Dist: pydantic>=2.7
Requires-Dist: python-dotenv>=1.0
Requires-Dist: pyyaml>=6.0.1
Requires-Dist: requests
Provides-Extra: cli
Requires-Dist: typer==0.12.3; extra == 'cli'
Provides-Extra: dev
Requires-Dist: coverage==7.5.1; extra == 'dev'
Requires-Dist: parameterized==0.9.0; extra == 'dev'
Requires-Dist: pytest-mock==3.14.0; extra == 'dev'
Requires-Dist: pytest>=8.2; extra == 'dev'
Provides-Extra: docs
Requires-Dist: griffe-fieldz==0.4.0; extra == 'docs'
Requires-Dist: mkdocs-gen-files==0.5.0; extra == 'docs'
Requires-Dist: mkdocs-literate-nav==0.6.1; extra == 'docs'
Requires-Dist: mkdocs-material==9.5.27; extra == 'docs'
Requires-Dist: mkdocstrings[python]==0.26.1; extra == 'docs'
